pybhcd.cpython-36m-darwin.so
pybhcd-0.5.post1.dist-info/METADATA
pybhcd-0.5.post1.dist-info/WHEEL
pybhcd-0.5.post1.dist-info/top_level.txt
pybhcd-0.5.post1.dist-info/RECORD
