Metadata-Version: 2.1
Name: pybhcd
Version: 0.5.post1
Summary: Bayesian Hierarchical Community Discovery
Home-page: https://github.com/zhaofeng-shu33/pybhcd
Author: blundellc, zhaofeng-shu33
Author-email: 616545598@qq.com
Maintainer: zhaofeng-shu33
Maintainer-email: 616545598@qq.com
License: Apache License Version 2.0
Platform: UNKNOWN
Classifier: Development Status :: 4 - Beta
Classifier: Programming Language :: Python :: 3.7
Classifier: Programming Language :: Python :: 3.6
Classifier: Operating System :: OS Independent
